README.md
setup.py
datakitchen_api_tools/DKConnection.py
datakitchen_api_tools/DKExceptions.py
datakitchen_api_tools/DKOrder.py
datakitchen_api_tools/__init__.py
datakitchen_api_tools/debug_scaffold.py
datakitchen_api_tools/dk_api_helpers.py
datakitchen_api_tools.egg-info/PKG-INFO
datakitchen_api_tools.egg-info/SOURCES.txt
datakitchen_api_tools.egg-info/dependency_links.txt
datakitchen_api_tools.egg-info/requires.txt
datakitchen_api_tools.egg-info/top_level.txt
datakitchen_api_tools/tests/__init__.py
datakitchen_api_tools/tests/test_helpers.py