Metadata-Version: 2.1
Name: datakitchen-api-tools
Version: 0.3.2
Summary: Python libray for working with DataKitchen's API
Home-page: https://github.com/
Author: Armand Halbert
Author-email: armand@datakitchen.io
License: UNKNOWN
Platform: UNKNOWN
Classifier: Programming Language :: Python :: 2
Classifier: Operating System :: OS Independent
